pymania
