Metadata-Version: 2.1
Name: pymania-controller
Version: 0.2.1
Summary: UNKNOWN
Home-page: https://gitlab.com/v7a/pymania
Author: v7a
License: UNKNOWN
Platform: UNKNOWN
Classifier: Programming Language :: Python :: 3.7
Classifier: License :: OSI Approved :: MIT License
Classifier: Operating System :: OS Independent
